manipulador_pdf/__init__.py
manipulador_pdf/configs/__init__.py
manipulador_pdf/configs/help_doc.py
manipulador_pdf/configs/info_hub.py
manipulador_pdf/configs/limpa_terminal.py
manipulador_pdf/configs/main_hub.py
manipulador_pdf/configs/process_option.py
manipulador_pdf/configs/salva_relatorio.py
manipulador_pdf/configs/update.py
manipulador_pdf/functions/__init__.py
manipulador_pdf/functions/boletos_bmp.py
manipulador_pdf/functions/boletos_cobranca.py
manipulador_pdf/functions/documentos_admissao.py
manipulador_pdf/functions/documentos_rescisao.py
manipulador_pdf/functions/fichas_de_registro.py
manipulador_pdf/functions/folha_rescisao_ferias.py
manipulador_pdf/functions/guias_fgts.py
manipulador_pdf/functions/img_functions.py
manipulador_pdf/functions/listagem_conferencia.py
manipulador_pdf/functions/nfs_curitiba.py
manipulador_pdf/functions/nfs_fortaleza.py
manipulador_pdf/functions/nfs_salvador.py
manipulador_pdf/functions/nfs_sorocaba.py
manipulador_pdf/functions/recibos_folk.py
manipulador_pdf/functions/recibos_pagamento.py
manipulador_pdf/functions/rel_servicos_adm.py
manipulador_pdf/functions/resumo_geral_mes_periodo.py
manipulador_pdf-0.0.35.dist-info/METADATA
manipulador_pdf-0.0.35.dist-info/WHEEL
manipulador_pdf-0.0.35.dist-info/top_level.txt
manipulador_pdf-0.0.35.dist-info/RECORD
