Metadata-Version: 2.1
Name: manipulador_pdf
Version: 0.0.35
Summary: Uma biblioteca para manipulação de arquivos .pdf.
Author: Luiz Gustavo Queiroz
Author-email: luizgusqueiroz@gmail.com
Requires-Dist: google-auth
Requires-Dist: google-auth-oauthlib
Requires-Dist: google-api-python-client
Requires-Dist: PyPDF2
Requires-Dist: pandas
Requires-Dist: tqdm
